genwatch/__init__.py
genwatch/_bases.py
genwatch/_generator_reporter.py
genwatch/_logger.py
genwatch/async_function_reporter.py
genwatch-0.1.1.dist-info/licenses/LICENSE
genwatch-0.1.1.dist-info/METADATA
genwatch-0.1.1.dist-info/WHEEL
genwatch-0.1.1.dist-info/top_level.txt
genwatch-0.1.1.dist-info/RECORD
