Metadata-Version: 2.4
Name: genwatch
Version: 0.1.1
Summary: Decorator for tracing Python generator internals
Author: Azema Shaik
License:                                  Apache License
Project-URL: Homepage, https://github.com/azema-shaik/genwatch
Keywords: generator,tracing,decorator
Requires-Python: >=3.10
License-File: LICENSE
Provides-Extra: test
Requires-Dist: pytest>=7.0; extra == "test"
Dynamic: license-file
